package b;

import com.sun.net.httpserver.HttpHandler;
import java.io.PrintWriter;

final class d
  implements HttpHandler
{
  private c a;
  private PrintWriter b;
  
  public d(c paramc, PrintWriter paramPrintWriter)
  {
    this.a = paramc;
    this.b = paramPrintWriter;
  }
  
  /* Error */
  public final void handle(com.sun.net.httpserver.HttpExchange arg1)
  {
    // Byte code:
    //   0: sipush 1028
    //   3: newarray <illegal type>
    //   5: astore_2
    //   6: new 21	java/lang/StringBuilder
    //   9: dup
    //   10: invokespecial 49	java/lang/StringBuilder:<init>	()V
    //   13: astore_3
    //   14: aconst_null
    //   15: astore 4
    //   17: new 13	java/io/InputStreamReader
    //   20: dup
    //   21: aload_1
    //   22: invokevirtual 31	com/sun/net/httpserver/HttpExchange:getRequestBody	()Ljava/io/InputStream;
    //   25: ldc 5
    //   27: invokespecial 35	java/io/InputStreamReader:<init>	(Ljava/io/InputStream;Ljava/lang/String;)V
    //   30: astore 5
    //   32: aload 5
    //   34: aload_2
    //   35: iconst_0
    //   36: sipush 1028
    //   39: invokevirtual 42	java/io/Reader:read	([CII)I
    //   42: dup
    //   43: istore 6
    //   45: iflt +15 -> 60
    //   48: aload_3
    //   49: aload_2
    //   50: iconst_0
    //   51: iload 6
    //   53: invokevirtual 52	java/lang/StringBuilder:append	([CII)Ljava/lang/StringBuilder;
    //   56: pop
    //   57: goto -25 -> 32
    //   60: aload 5
    //   62: invokevirtual 41	java/io/Reader:close	()V
    //   65: goto +55 -> 120
    //   68: astore 4
    //   70: aload 5
    //   72: invokevirtual 41	java/io/Reader:close	()V
    //   75: aload 4
    //   77: athrow
    //   78: astore_2
    //   79: aload 4
    //   81: ifnonnull +9 -> 90
    //   84: aload_2
    //   85: astore 4
    //   87: goto +15 -> 102
    //   90: aload 4
    //   92: aload_2
    //   93: if_acmpeq +9 -> 102
    //   96: aload 4
    //   98: aload_2
    //   99: invokevirtual 54	java/lang/Throwable:addSuppressed	(Ljava/lang/Throwable;)V
    //   102: aload 4
    //   104: athrow
    //   105: dup
    //   106: astore 4
    //   108: invokevirtual 43	java/io/UnsupportedEncodingException:printStackTrace	()V
    //   111: goto +9 -> 120
    //   114: dup
    //   115: astore 4
    //   117: invokevirtual 34	java/io/IOException:printStackTrace	()V
    //   120: aload_3
    //   121: invokevirtual 53	java/lang/StringBuilder:toString	()Ljava/lang/String;
    //   124: ldc 2
    //   126: ldc 1
    //   128: invokevirtual 47	java/lang/String:replaceAll	(Ljava/lang/String;Ljava/lang/String;)Ljava/lang/String;
    //   131: astore 4
    //   133: ldc 4
    //   135: astore_2
    //   136: aload_1
    //   137: sipush 200
    //   140: aload_2
    //   141: invokevirtual 46	java/lang/String:length	()I
    //   144: i2l
    //   145: invokevirtual 33	com/sun/net/httpserver/HttpExchange:sendResponseHeaders	(IJ)V
    //   148: aload_1
    //   149: invokevirtual 32	com/sun/net/httpserver/HttpExchange:getResponseBody	()Ljava/io/OutputStream;
    //   152: dup
    //   153: astore 5
    //   155: aload_2
    //   156: invokevirtual 45	java/lang/String:getBytes	()[B
    //   159: invokevirtual 37	java/io/OutputStream:write	([B)V
    //   162: aload 5
    //   164: invokevirtual 36	java/io/OutputStream:close	()V
    //   167: aload_0
    //   168: getfield 28	b/d:b	Ljava/io/PrintWriter;
    //   171: ifnull +45 -> 216
    //   174: getstatic 29	java/lang/System:out	Ljava/io/PrintStream;
    //   177: aload 4
    //   179: invokevirtual 38	java/io/PrintStream:println	(Ljava/lang/String;)V
    //   182: aload_0
    //   183: getfield 28	b/d:b	Ljava/io/PrintWriter;
    //   186: new 21	java/lang/StringBuilder
    //   189: dup
    //   190: aload 4
    //   192: invokestatic 48	java/lang/String:valueOf	(Ljava/lang/Object;)Ljava/lang/String;
    //   195: invokespecial 50	java/lang/StringBuilder:<init>	(Ljava/lang/String;)V
    //   198: ldc 2
    //   200: invokevirtual 51	java/lang/StringBuilder:append	(Ljava/lang/String;)Ljava/lang/StringBuilder;
    //   203: invokevirtual 53	java/lang/StringBuilder:toString	()Ljava/lang/String;
    //   206: invokevirtual 40	java/io/PrintWriter:write	(Ljava/lang/String;)V
    //   209: aload_0
    //   210: getfield 28	b/d:b	Ljava/io/PrintWriter;
    //   213: invokevirtual 39	java/io/PrintWriter:flush	()V
    //   216: aload_0
    //   217: getfield 27	b/d:a	Lb/c;
    //   220: getfield 24	b/c:a	Z
    //   223: ifne +19 -> 242
    //   226: aload_0
    //   227: getfield 27	b/d:a	Lb/c;
    //   230: iconst_1
    //   231: putfield 24	b/c:a	Z
    //   234: getstatic 29	java/lang/System:out	Ljava/io/PrintStream;
    //   237: ldc 3
    //   239: invokevirtual 38	java/io/PrintStream:println	(Ljava/lang/String;)V
    //   242: new 7	b/b
    //   245: dup
    //   246: aload 4
    //   248: invokespecial 30	b/b:<init>	(Ljava/lang/String;)V
    //   251: astore 6
    //   253: aload_0
    //   254: getfield 27	b/d:a	Lb/c;
    //   257: getfield 25	b/c:c	Ljava/lang/Object;
    //   260: dup
    //   261: astore_1
    //   262: monitorenter
    //   263: aload_0
    //   264: getfield 27	b/d:a	Lb/c;
    //   267: aload 6
    //   269: putfield 26	b/c:d	Lb/b;
    //   272: aload_1
    //   273: monitorexit
    //   274: return
    //   275: aload_1
    //   276: monitorexit
    //   277: athrow
    // Local variable table:
    //   start	length	slot	name	signature
    //   0	278	0	this	d
    //   5	45	2	arrayOfChar	char[]
    //   78	21	2	localThrowable	Throwable
    //   135	21	2	str	String
    //   13	108	3	localStringBuilder	StringBuilder
    //   15	1	4	localObject1	Object
    //   68	12	4	localObject2	Object
    //   85	162	4	localObject3	Object
    //   30	133	5	localObject4	Object
    //   43	9	6	i	int
    //   251	17	6	localb	b
    //   105	1	12	localUnsupportedEncodingException	java.io.UnsupportedEncodingException
    //   114	1	13	localIOException	java.io.IOException
    // Exception table:
    //   from	to	target	type
    //   32	60	68	finally
    //   17	78	78	finally
    //   14	105	105	java/io/UnsupportedEncodingException
    //   14	105	114	java/io/IOException
    //   263	274	275	finally
    //   275	277	275	finally
  }
}


/* Location:              C:\Program Files (x86)\FeedLess-Alpha\Client.jar!\b\d.class
 * Java compiler version: 7 (51.0)
 * JD-Core Version:       0.7.1
 */